flytekitplugins_optuna-1.16.12-py3.14-nspkg.pth
flytekitplugins/optuna/__init__.py
flytekitplugins/optuna/optimizer.py
flytekitplugins_optuna-1.16.12.dist-info/METADATA
flytekitplugins_optuna-1.16.12.dist-info/WHEEL
flytekitplugins_optuna-1.16.12.dist-info/entry_points.txt
flytekitplugins_optuna-1.16.12.dist-info/namespace_packages.txt
flytekitplugins_optuna-1.16.12.dist-info/top_level.txt
flytekitplugins_optuna-1.16.12.dist-info/RECORD
