Metadata-Version: 2.4
Name: flytekitplugins-optuna
Version: 1.16.12
Summary: Optuna plugin for flytekit
Author: flyteorg
Author-email: admin@flyte.org
License: apache2
Classifier: Intended Audience :: Science/Research
Classifier: Intended Audience :: Developers
Classifier: License :: OSI Approved :: Apache Software License
Classifier: Programming Language :: Python :: 3.9
Classifier: Programming Language :: Python :: 3.10
Classifier: Topic :: Scientific/Engineering
Classifier: Topic :: Scientific/Engineering :: Artificial Intelligence
Classifier: Topic :: Software Development
Classifier: Topic :: Software Development :: Libraries
Classifier: Topic :: Software Development :: Libraries :: Python Modules
Requires-Python: >=3.9
Requires-Dist: flytekit>=1.15.0
Requires-Dist: optuna<5.0.0,>=4.0.0
Requires-Dist: typing-extensions<5.0,>=4.10
Dynamic: author
Dynamic: author-email
Dynamic: classifier
Dynamic: license
Dynamic: requires-dist
Dynamic: requires-python
Dynamic: summary
